simple_ai_agents/__init__.py
simple_ai_agents/chat_agent.py
simple_ai_agents/chat_session.py
simple_ai_agents/cli.py
simple_ai_agents/external.py
simple_ai_agents/models.py
simple_ai_agents/prompts.py
simple_ai_agents/utils.py
simple_ai_agents-0.5.1.dist-info/LICENSE
simple_ai_agents-0.5.1.dist-info/METADATA
simple_ai_agents-0.5.1.dist-info/WHEEL
simple_ai_agents-0.5.1.dist-info/entry_points.txt
simple_ai_agents-0.5.1.dist-info/RECORD
