Metadata-Version: 2.1
Name: simple-ai-agents
Version: 0.5.1
Summary: A Python package for creating simple multi-agent workflows using various LLMs. The library extends the capabilities of Simple AI Chat by supporting over 100 LLM providers, structured responses, and multi-agent conversations, enabling easy experimentation, deployment, and orchestration of chatbots.
Author: Timothy Lin
Author-email: timothy0336@hotmail.com
Requires-Python: >=3.9,<4.0
Classifier: Programming Language :: Python :: 3
Classifier: Programming Language :: Python :: 3.9
Classifier: Programming Language :: Python :: 3.10
Classifier: Programming Language :: Python :: 3.11
Requires-Dist: click (>=8.1.7,<9.0.0)
Requires-Dist: instructor (>=1.4.1,<2.0.0)
Requires-Dist: litellm (>=1.47.0,<2.0.0)
Requires-Dist: openai (>=1.45.0,<2.0.0)
Requires-Dist: pydantic (>=2.4.0,<3.0.0)
Requires-Dist: python-dateutil (>=2.8.2,<3.0.0)
Requires-Dist: python-dotenv (>=1.0.0,<2.0.0)
Requires-Dist: rich (>=13.7.0,<14.0.0)
